assembly_uploader/__init__.py
assembly_uploader/assembly_manifest.py
assembly_uploader/ena_queries.py
assembly_uploader/release_study.py
assembly_uploader/study_xmls.py
assembly_uploader/submit_study.py
assembly_uploader/webin_utils.py
assembly_uploader-1.3.2.dist-info/licenses/LICENSE
assembly_uploader-1.3.2.dist-info/METADATA
assembly_uploader-1.3.2.dist-info/WHEEL
assembly_uploader-1.3.2.dist-info/entry_points.txt
assembly_uploader-1.3.2.dist-info/top_level.txt
assembly_uploader-1.3.2.dist-info/RECORD
