Metadata-Version: 2.4
Name: assembly_uploader
Version: 1.3.2
Summary: Python scripts to upload primary metagenome and metatranscriptome assemblies to ENA on a per-study basis. This script generates xmls to register a new study and create manifests necessary for submission with webin-cli.
Author-email: MGnify team <metagenomics-help@ebi.ac.uk>
License: Apache Software License 2.0
Keywords: bioinformatics,tool,metagenomics
Classifier: Programming Language :: Python :: 3.8
Classifier: Programming Language :: Python :: 3.9
Classifier: Programming Language :: Python :: 3.10
Classifier: Programming Language :: Python :: 3.11
Classifier: Development Status :: 5 - Production/Stable
Classifier: Intended Audience :: Science/Research
Classifier: Topic :: Scientific/Engineering :: Bio-Informatics
Classifier: License :: OSI Approved :: Apache Software License
Classifier: Operating System :: OS Independent
Requires-Python: >=3.8
License-File: LICENSE
Requires-Dist: requests==2.32.3
Provides-Extra: dev
Requires-Dist: pre-commit==3.6.0; extra == "dev"
Requires-Dist: black==24.4.2; extra == "dev"
Provides-Extra: test
Requires-Dist: pytest==8.2.2; extra == "test"
Requires-Dist: pytest-md==0.2.0; extra == "test"
Requires-Dist: pytest-workflow==2.1.0; extra == "test"
Requires-Dist: pytest-responses==0.5.1; extra == "test"
Dynamic: license-file
